Changelog.rst
Developer_Manual.rst
LICENSE.txt
MANIFEST.in
README.rst
pyproject.toml
setup.cfg
setup.py
SajadDE/Builtins.py
SajadDE/BytecodeCaching.py
SajadDE/Bytecodes.py
SajadDE/CacheCleanup.py
SajadDE/Constants.py
SajadDE/Errors.py
SajadDE/HardImportRegistry.py
SajadDE/MainControl.py
SajadDE/ModuleRegistry.py
SajadDE/OptionParsing.py
SajadDE/Options.py
SajadDE/OutputDirectories.py
SajadDE/PostProcessing.py
SajadDE/Progress.py
SajadDE/PythonFlavors.py
SajadDE/PythonOperators.py
SajadDE/PythonVersions.py
SajadDE/Serialization.py
SajadDE/SourceCodeReferences.py
SajadDE/Tracing.py
SajadDE/TreeXML.py
SajadDE/Variables.py
SajadDE/Version.py
SajadDE/__init__.py
SajadDE/__main__.py
SajadDE/__past__.py
SajadDE/build/Backend.scons
SajadDE/build/CCompilerVersion.scons
SajadDE/build/DataComposerInterface.py
SajadDE/build/Offsets.scons
SajadDE/build/Onefile.scons
SajadDE/build/SconsCaching.py
SajadDE/build/SconsCompilerSettings.py
SajadDE/build/SconsHacks.py
SajadDE/build/SconsInterface.py
SajadDE/build/SconsProgress.py
SajadDE/build/SconsSpawn.py
SajadDE/build/SconsUtils.py
SajadDE/build/__init__.py
SajadDE/build/include/SajadDE/allocator.h
SajadDE/build/include/SajadDE/builtins.h
SajadDE/build/include/SajadDE/calling.h
SajadDE/build/include/SajadDE/checkers.h
SajadDE/build/include/SajadDE/checksum_tools.h
SajadDE/build/include/SajadDE/compiled_asyncgen.h
SajadDE/build/include/SajadDE/compiled_cell.h
SajadDE/build/include/SajadDE/compiled_coroutine.h
SajadDE/build/include/SajadDE/compiled_frame.h
SajadDE/build/include/SajadDE/compiled_function.h
SajadDE/build/include/SajadDE/compiled_generator.h
SajadDE/build/include/SajadDE/compiled_method.h
SajadDE/build/include/SajadDE/constants.h
SajadDE/build/include/SajadDE/constants_blob.h
SajadDE/build/include/SajadDE/debug_settings.h
SajadDE/build/include/SajadDE/environment_variables.h
SajadDE/build/include/SajadDE/environment_variables_system.h
SajadDE/build/include/SajadDE/exception_groups.h
SajadQ.egg-info/PKG-INFO
SajadQ.egg-info/SOURCES.txt
SajadQ.egg-info/dependency_links.txt
SajadQ.egg-info/entry_points.txt
SajadQ.egg-info/not-zip-safe
SajadQ.egg-info/requires.txt
SajadQ.egg-info/top_level.txt
